README.md
setup.py
ingrunTools/JsonTools.py
ingrunTools/JsonToolsDjango.py
ingrunTools/RandomTools.py
ingrunTools/__init__.py
ingrunTools.egg-info/PKG-INFO
ingrunTools.egg-info/SOURCES.txt
ingrunTools.egg-info/dependency_links.txt
ingrunTools.egg-info/requires.txt
ingrunTools.egg-info/top_level.txt